setup.cfg
setup.py
pyieamods/__init__.py
pyieamods/pyieamods.py
pyieamods.egg-info/PKG-INFO
pyieamods.egg-info/SOURCES.txt
pyieamods.egg-info/dependency_links.txt
pyieamods.egg-info/requires.txt
pyieamods.egg-info/top_level.txt
test/__init__.py
test/test_pyideamods.py