Metadata-Version: 1.2
Name: pyieamods
Version: 1.0.4
Summary: wrapper around IEA Monthly Oil Data Service
Home-page: https://github.com/aeorxc/pyieamods
Author: aeorxc
Author-email: author@example.com
License: UNKNOWN
Project-URL: Source, https://github.com/aeorxc/pyieamods
Platform: UNKNOWN
Classifier: Programming Language :: Python :: 3
Classifier: License :: OSI Approved :: MIT License
Classifier: Operating System :: OS Independent
Requires-Python: >=3.6
